hydromill_amqp/__init__.py
hydromill_amqp/config.py
hydromill_amqp/connection.py
hydromill_amqp/marshaler.py
hydromill_amqp/publisher.py
hydromill_amqp/topology_builder.py
hydromill_amqp-0.1a9.dist-info/LICENSE
hydromill_amqp-0.1a9.dist-info/METADATA
hydromill_amqp-0.1a9.dist-info/WHEEL
hydromill_amqp-0.1a9.dist-info/RECORD
