Metadata-Version: 2.1
Name: hydromill-amqp
Version: 0.1a9
Summary: AMQP Pub/Sub for the Hydromill project. This project is a direct port of https://github.com/ThreeDotsLabs/watermill-amqp.
Home-page: https://github.com/mczudowski/hydromill-amqp
License: MIT
Author: Marek Czudowski
Author-email: marek.czudowski@pm.me
Requires-Python: >=3.8,<4.0
Classifier: License :: OSI Approved :: MIT License
Classifier: Programming Language :: Python :: 3
Classifier: Programming Language :: Python :: 3.8
Classifier: Programming Language :: Python :: 3.9
Classifier: Programming Language :: Python :: 3.10
Classifier: Programming Language :: Python :: 3.11
Classifier: Programming Language :: Python :: 3.12
Provides-Extra: elasticapm
Requires-Dist: aio-pika
Requires-Dist: elastic-apm ; extra == "elasticapm"
Requires-Dist: hydromill
Project-URL: Repository, https://github.com/mczudowski/hydromill-amqp
